event_manager/__init__.py
event_manager/event_manager.py
event_manager/fork_types.py
event_manager/tree.py
event_manager/listeners/__init__.py
event_manager/listeners/base.py
event_manager/listeners/batch.py
event_manager/listeners/scheduled.py
event_manager/listeners/simple.py
event_manager/queues/__init__.py
event_manager/queues/base.py
event_manager/queues/memory.py
pyeventmanager-0.5.6.dist-info/METADATA
pyeventmanager-0.5.6.dist-info/WHEEL
pyeventmanager-0.5.6.dist-info/RECORD
