Metadata-Version: 2.3
Name: pyeventmanager
Version: 0.5.6
Summary: Event management system for Python with support for Threading and Multiprocessing for task running.
Project-URL: Documentation, https://event-manager.jeofi.com
Project-URL: Homepage, https://event-manager.jeofi.com
Project-URL: Repository, https://github.com/JeordyR/PyEventManager
Project-URL: Issues, https://github.com/JeordyR/PyEventManager/issues
Author-email: Jeordy <JeordyR@users.noreply.github.com>
Classifier: Operating System :: OS Independent
Classifier: Programming Language :: Python :: 3.11
Classifier: Programming Language :: Python :: 3.12
Requires-Python: >=3.11
